gcp_log/__init__.py
gcp_log/_formatter.py
gcp_log/py.typed
gcp_log-1.0.1.dist-info/LICENSE
gcp_log-1.0.1.dist-info/WHEEL
gcp_log-1.0.1.dist-info/METADATA
gcp_log-1.0.1.dist-info/RECORD
