Metadata-Version: 2.1
Name: gcp-log
Version: 1.0.1
Summary: Format logs as GCP-compatible JSON.
Keywords: gcp,google,logging,logger
Author-email: Gram <git@orsinium.dev>
Requires-Python: >=3.8
Classifier: Development Status :: 5 - Production/Stable
Classifier: Intended Audience :: Developers
Classifier: License :: OSI Approved :: MIT License
Classifier: Programming Language :: Python
Classifier: Typing :: Typed
Requires-Dist: flake8 ; extra == "lint"
Requires-Dist: isort ; extra == "lint"
Requires-Dist: mypy ; extra == "lint"
Requires-Dist: unify ; extra == "lint"
Requires-Dist: pytest ; extra == "test"
Requires-Dist: pytest-cov ; extra == "test"
Project-URL: Source, https://github.com/orsinium-labs/gcp-log
Provides-Extra: lint
Provides-Extra: test
